proptools/__init__.py
proptools/constants.py
proptools/convection.py
proptools/convection_test.py
proptools/isentropic.py
proptools/isentropic_test.py
proptools/nonsimple_comp_flow.py
proptools/nozzle.py
proptools/nozzle_test.py
proptools/solid.py
proptools/solid_test.py
proptools/tank_structure.py
proptools/tank_structure_test.py
proptools/turbopump.py
proptools/turbopump_test.py
proptools/units.py
proptools/valve.py
proptools/valve_test.py
proptools/electric/__init__.py
proptools/electric/electric_test.py
proptools/electric/generic.py
proptools_rocket-0.0.2.dist-info/LICENSE
proptools_rocket-0.0.2.dist-info/METADATA
proptools_rocket-0.0.2.dist-info/WHEEL
proptools_rocket-0.0.2.dist-info/top_level.txt
proptools_rocket-0.0.2.dist-info/RECORD
